simple_history/__init__.py
simple_history/admin.py
simple_history/exceptions.py
simple_history/manager.py
simple_history/middleware.py
simple_history/models.py
simple_history/signals.py
simple_history/template_utils.py
simple_history/utils.py
simple_history/locale/ar/LC_MESSAGES/django.mo
simple_history/locale/ar/LC_MESSAGES/django.po
simple_history/locale/cs_CZ/LC_MESSAGES/django.mo
simple_history/locale/cs_CZ/LC_MESSAGES/django.po
simple_history/locale/de/LC_MESSAGES/django.mo
simple_history/locale/de/LC_MESSAGES/django.po
simple_history/locale/fr/LC_MESSAGES/django.mo
simple_history/locale/fr/LC_MESSAGES/django.po
simple_history/locale/id/LC_MESSAGES/django.mo
simple_history/locale/id/LC_MESSAGES/django.po
simple_history/locale/nb/LC_MESSAGES/django.mo
simple_history/locale/nb/LC_MESSAGES/django.po
simple_history/locale/pl/LC_MESSAGES/django.mo
simple_history/locale/pl/LC_MESSAGES/django.po
simple_history/locale/pt_BR/LC_MESSAGES/django.mo
simple_history/locale/pt_BR/LC_MESSAGES/django.po
simple_history/locale/ru_RU/LC_MESSAGES/django.mo
simple_history/locale/ru_RU/LC_MESSAGES/django.po
simple_history/locale/ur/LC_MESSAGES/django.mo
simple_history/locale/ur/LC_MESSAGES/django.po
simple_history/locale/zh_Hans/LC_MESSAGES/django.mo
simple_history/locale/zh_Hans/LC_MESSAGES/django.po
simple_history/management/__init__.py
simple_history/management/commands/__init__.py
simple_history/management/commands/clean_duplicate_history.py
simple_history/management/commands/clean_old_history.py
simple_history/management/commands/populate_history.py
simple_history/registry_tests/__init__.py
simple_history/registry_tests/models.py
simple_history/registry_tests/tests.py
simple_history/registry_tests/migration_test_app/__init__.py
simple_history/registry_tests/migration_test_app/models.py
simple_history/registry_tests/migration_test_app/migrations/0001_initial.py
django_simple_history-3.6.0.dist-info/AUTHORS.rst
django_simple_history-3.6.0.dist-info/LICENSE.txt
django_simple_history-3.6.0.dist-info/METADATA
django_simple_history-3.6.0.dist-info/WHEEL
django_simple_history-3.6.0.dist-info/top_level.txt
django_simple_history-3.6.0.dist-info/RECORD
