Metadata-Version: 2.1
Name: django-simple-history
Version: 3.6.0
Summary: Store model history and view/revert changes from admin site.
Home-page: https://github.com/jazzband/django-simple-history
Author: Corey Bertram
Author-email: corey@qr7.com
Maintainer: Trey Hunner
Project-URL: Documentation, https://django-simple-history.readthedocs.io/
Project-URL: Changelog, https://github.com/jazzband/django-simple-history/blob/master/CHANGES.rst
Project-URL: Source, https://github.com/jazzband/django-simple-history
Project-URL: Tracker, https://github.com/jazzband/django-simple-history/issues
Classifier: Development Status :: 5 - Production/Stable
Classifier: Framework :: Django
Classifier: Environment :: Web Environment
Classifier: Intended Audience :: Developers
Classifier: Framework :: Django
Classifier: Framework :: Django :: 3.2
Classifier: Framework :: Django :: 4.2
Classifier: Framework :: Django :: 5.0
Classifier: Programming Language :: Python
Classifier: Programming Language :: Python :: 3
Classifier: Programming Language :: Python :: 3.8
Classifier: Programming Language :: Python :: 3.9
Classifier: Programming Language :: Python :: 3.10
Classifier: Programming Language :: Python :: 3.11
Classifier: Programming Language :: Python :: 3.12
Classifier: Programming Language :: Python :: 3.13
Classifier: License :: OSI Approved :: BSD License
Requires-Python: >=3.8
License-File: LICENSE.txt
License-File: AUTHORS.rst
Requires-Dist: asgiref>=3.6
